quidam/__init__.py
quidam/core.py
quidam-1.23.dist-info/LICENSE
quidam-1.23.dist-info/METADATA
quidam-1.23.dist-info/WHEEL
quidam-1.23.dist-info/top_level.txt
quidam-1.23.dist-info/RECORD
