Metadata-Version: 2.1
Name: quidam
Version: 1.23
Summary: Permet de recupérer des informations grace a la fonction mot de passe oubliée de certains sites
Home-page: http://github.com/megadose/Quidam
Author: megadose
Author-email: UNKNOWN
License: UNKNOWN
Platform: UNKNOWN
Classifier: Programming Language :: Python
Classifier: License :: OSI Approved :: GNU General Public License v3 (GPLv3)
Requires-Dist: argparse
Requires-Dist: evolut
Requires-Dist: fake-useragent
Requires-Dist: requests
